LICENSE
MANIFEST.in
README.md
setup.py
OASYS2_SHADOW4.egg-info/PKG-INFO
OASYS2_SHADOW4.egg-info/SOURCES.txt
OASYS2_SHADOW4.egg-info/dependency_links.txt
OASYS2_SHADOW4.egg-info/entry_points.txt
OASYS2_SHADOW4.egg-info/not-zip-safe
OASYS2_SHADOW4.egg-info/requires.txt
OASYS2_SHADOW4.egg-info/top_level.txt
orangecontrib/__init__.py
orangecontrib/shadow4/__init__.py
orangecontrib/shadow4/menu/__init__.py
orangecontrib/shadow4/menu/ow_shadow4_menu.py
orangecontrib/shadow4/util/__init__.py
orangecontrib/shadow4/util/python_script.py
orangecontrib/shadow4/util/scanning.py
orangecontrib/shadow4/util/shadow4_objects.py
orangecontrib/shadow4/util/shadow4_util.py
orangecontrib/shadow4/util/srw.py
orangecontrib/shadow4/widgets/__init__.py
orangecontrib/shadow4/widgets/gui/__init__.py
orangecontrib/shadow4/widgets/gui/ow_abstract_lens.py
orangecontrib/shadow4/widgets/gui/ow_automatic_element.py
orangecontrib/shadow4/widgets/gui/ow_electron_beam.py
orangecontrib/shadow4/widgets/gui/ow_generic_element.py
orangecontrib/shadow4/widgets/gui/ow_optical_element.py
orangecontrib/shadow4/widgets/gui/ow_optical_element_with_surface_shape.py
orangecontrib/shadow4/widgets/gui/ow_optical_element_with_surface_shape_render.py
orangecontrib/shadow4/widgets/gui/ow_synchrotron_source.py
orangecontrib/shadow4/widgets/gui/plots.py
orangecontrib/shadow4/widgets/loops/__init__.py
orangecontrib/shadow4/widgets/loops/ow_accumulating_node_point.py
orangecontrib/shadow4/widgets/loops/ow_histogram_scan.py
orangecontrib/shadow4/widgets/loops/ow_seed_node_point.py
orangecontrib/shadow4/widgets/loops/icons/beam_accumulating.png
orangecontrib/shadow4/widgets/loops/icons/cycle.png
orangecontrib/shadow4/widgets/loops/icons/histogram_scan.png
orangecontrib/shadow4/widgets/loops/icons/loops.png
orangecontrib/shadow4/widgets/optics/__init__.py
orangecontrib/shadow4/widgets/optics/ow_beam_movements.py
orangecontrib/shadow4/widgets/optics/ow_crl.py
orangecontrib/shadow4/widgets/optics/ow_crystal.py
orangecontrib/shadow4/widgets/optics/ow_empty_element.py
orangecontrib/shadow4/widgets/optics/ow_grating.py
orangecontrib/shadow4/widgets/optics/ow_ideal_fzp.py
orangecontrib/shadow4/widgets/optics/ow_ideal_lens.py
orangecontrib/shadow4/widgets/optics/ow_lens.py
