Metadata-Version: 2.4
Name: OASYS2-SHADOW4
Version: 0.0.30
Summary: oasys2-shadow4: Oasys 2 widgets for shadow4
Home-page: https://github.com/oasys-kit/OASYS2-SHADOW4
Download-URL: https://github.com/oasys-kit/OASYS2-SHADOW4
Author: M. Sanchez del Rio, L. Rebuffi
Author-email: srio@esrf.eu
License: BSD3
Keywords: ray tracing,x-ray optics,oasys2
Classifier: Development Status :: 4 - Beta
Classifier: Environment :: X11 Applications :: Qt
Classifier: Environment :: Console
Classifier: Environment :: Plugins
Classifier: Programming Language :: Python
Classifier: Programming Language :: Python :: 3
Classifier: Intended Audience :: Science/Research
License-File: LICENSE
Requires-Dist: oasys2>=0.0.27
Requires-Dist: shadow4>=0.1.74
Requires-Dist: xoppylib>=1.0.46
Dynamic: author
Dynamic: author-email
Dynamic: classifier
Dynamic: description
Dynamic: description-content-type
Dynamic: download-url
Dynamic: home-page
Dynamic: keywords
Dynamic: license
Dynamic: license-file
Dynamic: requires-dist
Dynamic: summary
